config_controller_predeployed/__init__.py
config_controller_predeployed/address.py
config_controller_predeployed/config_controller_generator.py
config_controller_predeployed/artifacts/ConfigController.json
config_controller_predeployed/artifacts/ConfigController.meta.json
test/__init__.py
test/test_cc_generator.py
test/tools/__init__.py
test/tools/test_predeployed.py
test/tools/test_solidity_project.py
config_controller_predeployed-1.1.0.dist-info/METADATA
config_controller_predeployed-1.1.0.dist-info/WHEEL
config_controller_predeployed-1.1.0.dist-info/top_level.txt
config_controller_predeployed-1.1.0.dist-info/RECORD
