Metadata-Version: 2.1
Name: config-controller-predeployed
Version: 1.1.0
Summary: A tool for generating predeployed config controller smart contract
Home-page: https://github.com/skalenetwork/config-controller
Author: SKALE Labs
Author-email: support@skalelabs.com
Keywords: skale,predeployed
Classifier: Development Status :: 5 - Production/Stable
Classifier: Intended Audience :: Developers
Classifier: License :: OSI Approved :: GNU Affero General Public License v3 or later (AGPLv3+)
Classifier: Natural Language :: English
Classifier: Programming Language :: Python :: 3.7
Requires-Python: >=3.7,<4
Requires-Dist: predeployed-generator >=1.2.0
Provides-Extra: dev
Requires-Dist: flake8 ==3.7.9 ; extra == 'dev'
Requires-Dist: twine ==5.1.1 ; extra == 'dev'
Requires-Dist: pytest ==6.2.5 ; extra == 'dev'
Requires-Dist: python-dotenv ; extra == 'dev'
Provides-Extra: linter
Requires-Dist: flake8 ==3.7.9 ; extra == 'linter'
